bot_bin/__init__.py
bot_bin/bot.py
bot_bin/debug.py
bot_bin/misc.py
bot_bin/socket.py
bot_bin/sql.py
bot_bin/stats.py
bot_bin/systemd.py
bot_bin-2.1.0.dist-info/LICENSE.md
bot_bin-2.1.0.dist-info/METADATA
bot_bin-2.1.0.dist-info/WHEEL
bot_bin-2.1.0.dist-info/top_level.txt
bot_bin-2.1.0.dist-info/RECORD
