Metadata-Version: 2.1
Name: bot-bin
Version: 2.1.0
Summary: Shared cogs and utilities for use in Discord bots
Home-page: https://github.com/ioistired/bot-bin
Author: @lambda.dance
License: BlueOak-1.0.0
Classifier: Development Status :: 5 - Production/Stable
Classifier: Framework :: AsyncIO
Classifier: Intended Audience :: Developers
Classifier: Natural Language :: English
Classifier: Operating System :: OS Independent
Classifier: Programming Language :: Python :: 3.8
Classifier: Programming Language :: Python :: 3.9
Classifier: Programming Language :: Python :: 3.10
Classifier: Programming Language :: Python :: 3.11
Classifier: Programming Language :: Python :: 3.12
Classifier: Topic :: Internet
Classifier: Topic :: Utilities
Classifier: Topic :: Communications :: Chat
Requires-Python: >=3.6.0
License-File: LICENSE.md
Requires-Dist: discord.py <3.0.0,>=2.3.2
Requires-Dist: humanize
Requires-Dist: python-dateutil
Requires-Dist: objgraph
Provides-Extra: sql
Requires-Dist: aiocontextvars >=0.2.2 ; extra == 'sql'
Requires-Dist: asyncpg ; extra == 'sql'
Requires-Dist: prettytable ; extra == 'sql'
Provides-Extra: uvloop
Requires-Dist: uvloop <1.0.0,>=0.14.0 ; extra == 'uvloop'
